[
  {
    "questionText": "বৃষ্টির সময় পোলের ওপর কাজ করা বিপজ্জনক কেন?",
    "options": [
      "কারণ ঠান্ডা লেগে যেতে পারে",
      "কারণ পৃষ্ঠ পিচ্ছিল হয়ে যায় এবং ফ্ল্যাশওভারের ঝুঁকি বাড়ে",
      "কারণ পোশাক ভিজে যায়",
      "কারণ কাজ করতে দেরি হয়"
    ],
    "correctAnswerIndex": 1
  },
  {
    "questionText": "বজ্রপাতের সময় একজন লাইনম্যানের জন্য সবচেয়ে নিরাপদ জায়গা কোনটি?",
    "options": [
      "পোলের ওপরে",
      "একটি বড় গাছের নিচে",
      "খোলা মাঠে শুয়ে পড়া",
      "সম্পূর্ণরূপে বন্ধ একটি গাড়ি বা বিল্ডিংয়ের ভেতরে"
    ],
    "correctAnswerIndex": 3
  },
  {
    "questionText": "প্রবল বাতাসে ওভারহেড তারগুলোর 'গ্যালোপিং' বা দোলনার ফলে কী বিপদ হতে পারে?",
    "options": [
      "তারগুলো ছিঁড়ে যেতে পারে",
      "বিভিন্ন ফেজের তার একে অপরের সংস্পর্শে এসে শর্ট সার্কিট হতে পারে",
      "তারগুলো আরও মজবুত হয়ে যায়",
      "শব্দ দূষণ হয়"
    ],
    "correctAnswerIndex": 1
  },
  {
    "questionText": "'থার্টি-থার্টি রুল' (30-30 Rule) অনুযায়ী, বজ্রের ঝলক দেখার কত সেকেন্ডের মধ্যে শব্দ শুনলে আপনার কাজ বন্ধ করে দেওয়া উচিত?",
    "options": [
      "৬০ সেকেন্ড",
      "১০ সেকেন্ড",
      "৩০ সেকেন্ডের কম সময়ে",
      "৪৫ সেকেন্ড"
    ],
    "correctAnswerIndex": 2
  },
  {
    "questionText": "আর্দ্র এবং ভেজা আবহাওয়ায় বাতাসের ডাই-ইলেকট্রিক স্ট্রেন্থের কী পরিবর্তন হয়?",
    "options": [
      "বেড়ে যায়",
      "কমে যায়, ফলে আর্ক ফ্ল্যাশের সম্ভাবনা বাড়ে",
      "একই থাকে",
      "শূন্য হয়ে যায়"
    ],
    "correctAnswerIndex": 1
  },
  {
    "questionText": "একজন লাইনম্যান হিসেবে, অনিরাপদ আবহাওয়ায় কাজ করতে 'না' বলাটা কিসের লক্ষণ?",
    "options": [
      "ভীরুতা",
      "অলসতা",
      "পেশাদারিত্ব এবং দায়িত্ববোধ",
      "অভিজ্ঞতার অভাব"
    ],
    "correctAnswerIndex": 2
  },
  {
    "questionText": "মিথ: 'রাবারের জুতো আর গ্লাভস পরা থাকলে বজ্রপাতে কিছু হবে না'—এই ধারণাটি ভুল কেন?",
    "options": [
      "কারণ রাবার বিদ্যুৎ পরিবহন করে",
      "কারণ বজ্রপাতের प्रचंड ভোল্টেজ এবং কারেন্টের সামনে PPE সুরক্ষা দিতে পারে না",
      "কারণ বৃষ্টিতে রাবার কাজ করে না",
      "কারণ এটি শুধুমাত্র একটি ধারণা"
    ],
    "correctAnswerIndex": 1
  },
  {
    "questionText": "বজ্রপাতের সময় মাটিতে আঘাত হানলে, 'স্টেপ পটেনশিয়াল' থেকে বাঁচতে আপনার কী করা উচিত?",
    "options": [
      "বড় বড় পদক্ষেপ ফেলে দৌড়ে পালানো",
      "মাটিতে শুয়ে পড়া",
      "দুই পা একসাথে রেখে ছোট ছোট পদক্ষেপে নিরাপদ স্থানে যাওয়া",
      "এক পায়ে লাফিয়ে যাওয়া"
    ],
    "correctAnswerIndex": 2
  },
  {
    "questionText": "হঠাৎ প্রবল বাতাস শুরু হলে, পোলের ওপর কাজ করার সময় আপনার প্রথম কাজ কী?",
    "options": [
      "তাড়াতাড়ি কাজটি শেষ করার চেষ্টা করা",
      "বাতাসের বিরুদ্ধে শক্ত হয়ে দাঁড়িয়ে থাকা",
      "সাবধানে এবং অবিলম্বে নিচে নেমে আসা",
      "সুপারভাইজারকে ফোন করা"
    ],
    "correctAnswerIndex": 2
  },
  {
    "questionText": "কোন পরিস্থিতিতে বৃষ্টির সময় জরুরি কাজ করা যেতে পারে?",
    "options": [
      "হালকা বৃষ্টি হলে",
      "শুধুমাত্র দিনের বেলায়",
      "যদি বজ্রপাত না হয় এবং সর্বোচ্চ সতর্কতা অবলম্বন করা হয়",
      "কখনোই নয়"
    ],
    "correctAnswerIndex": 2
  },
  {
    "questionText": "কাজের জায়গায় পৌঁছানোর পর আবহাওয়া সংক্রান্ত কোন পরিকল্পনাটি করে রাখা উচিত?",
    "options": [
      "কখন চা খাওয়া হবে",
      "হঠাৎ আবহাওয়া খারাপ হলে নিরাপদ আশ্রয়ের জায়গা কোনটি হবে",
      "কোথায় যন্ত্রপাতি রাখা হবে",
      "কত তাড়াতাড়ি কাজ শেষ করা যাবে"
    ],
    "correctAnswerIndex": 1
  },
  {
    "questionText": "ভারী বৃষ্টিতে 'দৃশ্যমানতা কমে যাওয়া' (Reduced Visibility) কেন একটি বড় বিপদ?",
    "options": [
      "কারণ রাস্তা খুঁজে পাওয়া যায় না",
      "কারণ আপনি ওপরের লাইভ তার বা অন্য বিপদ স্পষ্টভাবে দেখতে পান না",
      "কারণ সহকর্মীকে চেনা যায় না",
      "কারণ মন খারাপ হয়ে যায়"
    ],
    "correctAnswerIndex": 1
  },
  {
    "questionText": "সুপারভাইজার চাপ দেওয়া সত্ত্বেও যদি আপনার মনে হয় আবহাওয়া নিরাপদ নয়, আপনার কী করা উচিত?",
    "options": [
      "চুপচাপ কাজ করা",
      "আপনার উদ্বেগের কথা স্পষ্টভাবে এবং বিনীতভাবে জানানো",
      "অন্য কোনো সহকর্মীকে কাজটি করতে বলা",
      "অসুস্থতার ভান করা"
    ],
    "correctAnswerIndex": 1
  },
  {
    "questionText": "কাজ শুরুর আগে আবহাওয়ার পূর্বাভাস পরীক্ষা করা কেন একটি ভালো অভ্যাস?",
    "options": [
      "এটি শুধু একটি নিয়ম",
      "যাতে দিনের কাজের পরিকল্পনা করা যায় এবং সম্ভাব্য বিপদ সম্পর্কে আগে থেকে সচেতন থাকা যায়",
      "যাতে ছাতা আনা যাবে কিনা তা বোঝা যায়",
      "যাতে সুপারভাইজারকে দেখানো যায়"
    ],
    "correctAnswerIndex": 1
  },
  {
    "questionText": "বজ্রপাতের সময় ধাতব মই বা টাওয়ারের কাছে থাকা বিপজ্জনক কেন?",
    "options": [
      "কারণ এগুলো ঠান্ডা থাকে",
      "কারণ ধাতু বজ্রপাতকে আকর্ষণ করে এবং একটি সহজ পথ তৈরি করে দেয়",
      "কারণ এগুলোতে মরিচা ধরে",
      "কারণ এগুলো খুব লম্বা হয়"
    ],
    "correctAnswerIndex": 1
  },
  {
    "questionText": "আপনার ভেজা পোশাক এবং PPE আপনার জন্য কী নতুন বিপদ তৈরি করতে পারে?",
    "options": [
      "এগুলো ভারী হয়ে যায়",
      "এগুলোর ইনসুলেটিং ক্ষমতা কমে যায়",
      "দেখতে খারাপ লাগে",
      "এগুলো থেকে দুর্গন্ধ বেরোয়"
    ],
    "correctAnswerIndex": 1
  },
  {
    "questionText": "কোন ধরনের মেঘ বজ্রপাতের পূর্বাভাস দেয়?",
    "options": [
      "সাদা, হালকা মেঘ",
      "লম্বা, পাতলা মেঘ",
      "ঘন, কালো এবং উল্লম্বভাবে লম্বা মেঘ (কিউমুলোনিম্বাস)",
      "ছিটানো মেঘ"
    ],
    "correctAnswerIndex": 2
  },
  {
    "questionText": "পোলের ওপরে থাকাকালীন যদি আপনার মাথার চুল খাড়া হয়ে যায় বা ত্বক শিরশির করে, এটি কিসের লক্ষণ?",
    "options": [
      "ঠান্ডা লাগার লক্ষণ",
      "ভয় পাওয়ার লক্ষণ",
      "আপনার आसपास বজ্রপাত হওয়ার চরম সম্ভাবনার লক্ষণ",
      "উচ্চতার কারণে এমন হচ্ছে"
    ],
    "correctAnswerIndex": 2
  },
  {
    "questionText": "শীতকালে কুয়াশার মধ্যে কাজ করার প্রধান চ্যালেঞ্জ কী?",
    "options": [
      "খুব বেশি ঠান্ডা লাগা",
      "দৃশ্যমানতা কমে যাওয়া এবং পৃষ্ঠ ভিজে পিচ্ছিল হয়ে যাওয়া",
      "সহকর্মীদের সাথে কথা বলতে অসুবিধা হওয়া",
      "দিন ছোট হওয়া"
    ],
    "correctAnswerIndex": 1
  },
  {
    "questionText": "আপনার 'প্রবৃত্তি' বা 'ইনস্টিংক্ট' যদি বলে যে আবহাওয়া নিরাপদ নয়, আপনার কী করা উচিত?",
    "options": [
      "এটিকে উপেক্ষা করা কারণ এটি অবৈজ্ঞানিক",
      "আপনার অভিজ্ঞতা এবং প্রবৃত্তিকে সম্মান করা এবং পুনরায় পরিস্থিতি মূল্যায়ন করা",
      "অন্যদের জিজ্ঞাসা করা",
      "লটারি করা"
    ],
    "correctAnswerIndex": 1
  }
]


